douglog/__init__.py
douglog/douglog.py
douglog-0.2.6.dist-info/licenses/LICENSE
douglog-0.2.6.dist-info/METADATA
douglog-0.2.6.dist-info/WHEEL
douglog-0.2.6.dist-info/entry_points.txt
douglog-0.2.6.dist-info/top_level.txt
douglog-0.2.6.dist-info/RECORD
