Metadata-Version: 2.4
Name: douglog
Version: 0.2.6
Summary: Simple logging CLI tool
Author-email: Douglas Keller <dg.kllr.jr@gmail.com>
License: MIT License
Project-URL: Homepage, https://github.com/dkllrjr/douglog
Project-URL: Repository, https://github.com/dkllrjr/douglog.git
Requires-Python: >=3.12.0
License-File: LICENSE
Requires-Dist: click<=8.1.7
Requires-Dist: numpy
Dynamic: license-file
